kidronekit/__init__.py
kidronekit/lib.py
kidronekit/mavlink.py
kidronekit/util.py
kidronekit-1.0.0.dist-info/LICENSE
kidronekit-1.0.0.dist-info/METADATA
kidronekit-1.0.0.dist-info/WHEEL
kidronekit-1.0.0.dist-info/top_level.txt
kidronekit-1.0.0.dist-info/zip-safe
kidronekit-1.0.0.dist-info/RECORD
