Metadata-Version: 2.1
Name: kidronekit
Version: 1.0.0
Summary: Premium extended version of dronekit.
Home-page: https://github.com/kirinslab/kidronekit.git
Author: 3D Robotics, Kirinlab
Author-email: tim@3drobotics.com, kevinh@geeksville.com, haiquantran2897@gmail.com
License: apache
Classifier: Development Status :: 5 - Production/Stable
Classifier: Environment :: Console
Classifier: Intended Audience :: Science/Research
Classifier: License :: OSI Approved :: Apache Software License
Classifier: Operating System :: OS Independent
Classifier: Programming Language :: Python :: 3
Classifier: Topic :: Scientific/Engineering
License-File: LICENSE
Requires-Dist: pymavlink (>=2.2.20)
Requires-Dist: monotonic (>=1.3)
